napari_woggle_opacity/__init__.py
napari_woggle_opacity/_widget.py
napari_woggle_opacity/napari.yaml
napari_woggle_opacity/_tests/__init__.py
napari_woggle_opacity-0.0.1.dist-info/LICENSE
napari_woggle_opacity-0.0.1.dist-info/METADATA
napari_woggle_opacity-0.0.1.dist-info/WHEEL
napari_woggle_opacity-0.0.1.dist-info/entry_points.txt
napari_woggle_opacity-0.0.1.dist-info/top_level.txt
napari_woggle_opacity-0.0.1.dist-info/RECORD
